<?xml version="1.0" ?>
<template encoding-version="1.1">
  <description>Read an API search string from SQS. Retrieve the entries by iterating through 'next' fields
Push retrieved records to SQS for further processing.</description>
  <groupId>830049f6-015f-1000-7540-d97f08f40984</groupId>
  <name>DPN-Query-Bags</name>
  <snippet>
    <connections>
      <id>9f3e188b-87a2-3b1e-0000-000000000000</id>
      <parentGroupId>02247fc8-6d6e-386b-0000-000000000000</parentGroupId>
      <backPressureDataSizeThreshold>1 GB</backPressureDataSizeThreshold>
      <backPressureObjectThreshold>10000</backPressureObjectThreshold>
      <destination>
        <groupId>02247fc8-6d6e-386b-0000-000000000000</groupId>
        <id>5ea6d01d-6557-3f54-0000-000000000000</id>
        <type>PROCESSOR</type>
      </destination>
      <flowFileExpiration>0 sec</flowFileExpiration>
      <labelIndex>1</labelIndex>
      <name></name>
      <selectedRelationships>failure</selectedRelationships>
      <source>
        <groupId>02247fc8-6d6e-386b-0000-000000000000</groupId>
        <id>5b12ab24-fe05-3f7b-0000-000000000000</id>
        <type>PROCESSOR</type>
      </source>
      <zIndex>0</zIndex>
    </connections>
    <connections>
      <id>abfa55c4-4520-365b-0000-000000000000</id>
      <parentGroupId>02247fc8-6d6e-386b-0000-000000000000</parentGroupId>
      <backPressureDataSizeThreshold>1 GB</backPressureDataSizeThreshold>
      <backPressureObjectThreshold>10000</backPressureObjectThreshold>
      <destination>
        <groupId>02247fc8-6d6e-386b-0000-000000000000</groupId>
        <id>b0bfed8e-5442-3ee8-0000-000000000000</id>
        <type>PROCESSOR</type>
      </destination>
      <flowFileExpiration>0 sec</flowFileExpiration>
      <labelIndex>1</labelIndex>
      <name></name>
      <selectedRelationships>unmatched</selectedRelationships>
      <source>
        <groupId>02247fc8-6d6e-386b-0000-000000000000</groupId>
        <id>80882335-0433-3769-0000-000000000000</id>
        <type>PROCESSOR</type>
      </source>
      <zIndex>0</zIndex>
    </connections>
    <connections>
      <id>b50981b6-6ee8-34eb-0000-000000000000</id>
      <parentGroupId>02247fc8-6d6e-386b-0000-000000000000</parentGroupId>
      <backPressureDataSizeThreshold>1 GB</backPressureDataSizeThreshold>
      <backPressureObjectThreshold>10000</backPressureObjectThreshold>
      <destination>
        <groupId>02247fc8-6d6e-386b-0000-000000000000</groupId>
        <id>f9d69938-e784-361c-0000-000000000000</id>
        <type>PROCESSOR</type>
      </destination>
      <flowFileExpiration>0 sec</flowFileExpiration>
      <labelIndex>1</labelIndex>
      <name></name>
      <selectedRelationships>matched</selectedRelationships>
      <source>
        <groupId>02247fc8-6d6e-386b-0000-000000000000</groupId>
        <id>80882335-0433-3769-0000-000000000000</id>
        <type>PROCESSOR</type>
      </source>
      <zIndex>0</zIndex>
    </connections>
    <connections>
      <id>bad89523-6a5e-33d8-0000-000000000000</id>
      <parentGroupId>02247fc8-6d6e-386b-0000-000000000000</parentGroupId>
      <backPressureDataSizeThreshold>1 GB</backPressureDataSizeThreshold>
      <backPressureObjectThreshold>10000</backPressureObjectThreshold>
      <destination>
        <groupId>02247fc8-6d6e-386b-0000-000000000000</groupId>
        <id>5ea6d01d-6557-3f54-0000-000000000000</id>
        <type>PROCESSOR</type>
      </destination>
      <flowFileExpiration>0 sec</flowFileExpiration>
      <labelIndex>1</labelIndex>
      <name></name>
      <selectedRelationships>failure</selectedRelationships>
      <source>
        <groupId>02247fc8-6d6e-386b-0000-000000000000</groupId>
        <id>80882335-0433-3769-0000-000000000000</id>
        <type>PROCESSOR</type>
      </source>
      <zIndex>0</zIndex>
    </connections>
    <connections>
      <id>bccd0ef4-2262-31b5-0000-000000000000</id>
      <parentGroupId>02247fc8-6d6e-386b-0000-000000000000</parentGroupId>
      <backPressureDataSizeThreshold>1 GB</backPressureDataSizeThreshold>
      <backPressureObjectThreshold>10000</backPressureObjectThreshold>
      <destination>
        <groupId>02247fc8-6d6e-386b-0000-000000000000</groupId>
        <id>c7e8f2c1-f381-3540-0000-000000000000</id>
        <type>PROCESSOR</type>
      </destination>
      <flowFileExpiration>0 sec</flowFileExpiration>
      <labelIndex>1</labelIndex>
      <name></name>
      <selectedRelationships>success</selectedRelationships>
      <source>
        <groupId>02247fc8-6d6e-386b-0000-000000000000</groupId>
        <id>7ce9fc67-bfde-3483-0000-000000000000</id>
        <type>PROCESSOR</type>
      </source>
      <zIndex>0</zIndex>
    </connections>
    <connections>
      <id>bdaf67bc-3b37-3467-0000-000000000000</id>
      <parentGroupId>02247fc8-6d6e-386b-0000-000000000000</parentGroupId>
      <backPressureDataSizeThreshold>1 GB</backPressureDataSizeThreshold>
      <backPressureObjectThreshold>10000</backPressureObjectThreshold>
      <destination>
        <groupId>02247fc8-6d6e-386b-0000-000000000000</groupId>
        <id>6a12dc93-964a-3587-0000-000000000000</id>
        <type>PROCESSOR</type>
      </destination>
      <flowFileExpiration>0 sec</flowFileExpiration>
      <labelIndex>1</labelIndex>
      <name></name>
      <selectedRelationships>success</selectedRelationships>
      <source>
        <groupId>02247fc8-6d6e-386b-0000-000000000000</groupId>
        <id>02cb0aec-fd02-3a41-0000-000000000000</id>
        <type>PROCESSOR</type>
      </source>
      <zIndex>0</zIndex>
    </connections>
    <connections>
      <id>c46fe14e-7874-3ad9-0000-000000000000</id>
      <parentGroupId>02247fc8-6d6e-386b-0000-000000000000</parentGroupId>
      <backPressureDataSizeThreshold>1 GB</backPressureDataSizeThreshold>
      <backPressureObjectThreshold>10000</backPressureObjectThreshold>
      <destination>
        <groupId>02247fc8-6d6e-386b-0000-000000000000</groupId>
        <id>5ea6d01d-6557-3f54-0000-000000000000</id>
        <type>PROCESSOR</type>
      </destination>
      <flowFileExpiration>0 sec</flowFileExpiration>
      <labelIndex>1</labelIndex>
      <name></name>
      <selectedRelationships>failure</selectedRelationships>
      <source>
        <groupId>02247fc8-6d6e-386b-0000-000000000000</groupId>
        <id>7ce9fc67-bfde-3483-0000-000000000000</id>
        <type>PROCESSOR</type>
      </source>
      <zIndex>0</zIndex>
    </connections>
    <connections>
      <id>d2dbcd24-c420-3ac4-0000-000000000000</id>
      <parentGroupId>02247fc8-6d6e-386b-0000-000000000000</parentGroupId>
      <backPressureDataSizeThreshold>1 GB</backPressureDataSizeThreshold>
      <backPressureObjectThreshold>10000</backPressureObjectThreshold>
      <destination>
        <groupId>02247fc8-6d6e-386b-0000-000000000000</groupId>
        <id>80882335-0433-3769-0000-000000000000</id>
        <type>PROCESSOR</type>
      </destination>
      <flowFileExpiration>0 sec</flowFileExpiration>
      <labelIndex>1</labelIndex>
      <name></name>
      <selectedRelationships>output stream</selectedRelationships>
      <source>
        <groupId>02247fc8-6d6e-386b-0000-000000000000</groupId>
        <id>6a12dc93-964a-3587-0000-000000000000</id>
        <type>PROCESSOR</type>
      </source>
      <zIndex>0</zIndex>
    </connections>
    <connections>
      <id>da9a83d0-f45a-39c9-0000-000000000000</id>
      <parentGroupId>02247fc8-6d6e-386b-0000-000000000000</parentGroupId>
      <backPressureDataSizeThreshold>1 GB</backPressureDataSizeThreshold>
      <backPressureObjectThreshold>10000</backPressureObjectThreshold>
      <destination>
        <groupId>02247fc8-6d6e-386b-0000-000000000000</groupId>
        <id>0d0ce7fd-4ad9-3a20-0000-000000000000</id>
        <type>PROCESSOR</type>
      </destination>
      <flowFileExpiration>0 sec</flowFileExpiration>
      <labelIndex>1</labelIndex>
      <name></name>
      <selectedRelationships>success</selectedRelationships>
      <source>
        <groupId>02247fc8-6d6e-386b-0000-000000000000</groupId>
        <id>5b12ab24-fe05-3f7b-0000-000000000000</id>
        <type>PROCESSOR</type>
      </source>
      <zIndex>0</zIndex>
    </connections>
    <connections>
      <id>f9f80ca0-74fc-3e48-0000-000000000000</id>
      <parentGroupId>02247fc8-6d6e-386b-0000-000000000000</parentGroupId>
      <backPressureDataSizeThreshold>1 GB</backPressureDataSizeThreshold>
      <backPressureObjectThreshold>10000</backPressureObjectThreshold>
      <destination>
        <groupId>02247fc8-6d6e-386b-0000-000000000000</groupId>
        <id>5ea6d01d-6557-3f54-0000-000000000000</id>
        <type>PROCESSOR</type>
      </destination>
      <flowFileExpiration>0 sec</flowFileExpiration>
      <labelIndex>1</labelIndex>
      <name></name>
      <selectedRelationships>failure</selectedRelationships>
      <source>
        <groupId>02247fc8-6d6e-386b-0000-000000000000</groupId>
        <id>d34db8ff-b684-387c-0000-000000000000</id>
        <type>PROCESSOR</type>
      </source>
      <zIndex>0</zIndex>
    </connections>
    <connections>
      <id>ff8711b9-02d5-3afb-0000-000000000000</id>
      <parentGroupId>02247fc8-6d6e-386b-0000-000000000000</parentGroupId>
      <backPressureDataSizeThreshold>1 GB</backPressureDataSizeThreshold>
      <backPressureObjectThreshold>10000</backPressureObjectThreshold>
      <destination>
        <groupId>02247fc8-6d6e-386b-0000-000000000000</groupId>
        <id>7ce9fc67-bfde-3483-0000-000000000000</id>
        <type>PROCESSOR</type>
      </destination>
      <flowFileExpiration>0 sec</flowFileExpiration>
      <labelIndex>1</labelIndex>
      <name></name>
      <selectedRelationships>matched</selectedRelationships>
      <source>
        <groupId>02247fc8-6d6e-386b-0000-000000000000</groupId>
        <id>d34db8ff-b684-387c-0000-000000000000</id>
        <type>PROCESSOR</type>
      </source>
      <zIndex>0</zIndex>
    </connections>
    <connections>
      <id>16266c98-ef93-39ba-0000-000000000000</id>
      <parentGroupId>02247fc8-6d6e-386b-0000-000000000000</parentGroupId>
      <backPressureDataSizeThreshold>1 GB</backPressureDataSizeThreshold>
      <backPressureObjectThreshold>10000</backPressureObjectThreshold>
      <destination>
        <groupId>02247fc8-6d6e-386b-0000-000000000000</groupId>
        <id>5ea6d01d-6557-3f54-0000-000000000000</id>
        <type>PROCESSOR</type>
      </destination>
      <flowFileExpiration>0 sec</flowFileExpiration>
      <labelIndex>1</labelIndex>
      <name></name>
      <selectedRelationships>failure</selectedRelationships>
      <source>
        <groupId>02247fc8-6d6e-386b-0000-000000000000</groupId>
        <id>c7e8f2c1-f381-3540-0000-000000000000</id>
        <type>PROCESSOR</type>
      </source>
      <zIndex>0</zIndex>
    </connections>
    <connections>
      <id>1dd451bd-5972-3a1b-0000-000000000000</id>
      <parentGroupId>02247fc8-6d6e-386b-0000-000000000000</parentGroupId>
      <backPressureDataSizeThreshold>1 GB</backPressureDataSizeThreshold>
      <backPressureObjectThreshold>10000</backPressureObjectThreshold>
      <destination>
        <groupId>02247fc8-6d6e-386b-0000-000000000000</groupId>
        <id>0d0ce7fd-4ad9-3a20-0000-000000000000</id>
        <type>PROCESSOR</type>
      </destination>
      <flowFileExpiration>0 sec</flowFileExpiration>
      <labelIndex>1</labelIndex>
      <name></name>
      <selectedRelationships>success</selectedRelationships>
      <source>
        <groupId>02247fc8-6d6e-386b-0000-000000000000</groupId>
        <id>c7e8f2c1-f381-3540-0000-000000000000</id>
        <type>PROCESSOR</type>
      </source>
      <zIndex>0</zIndex>
    </connections>
    <connections>
      <id>4967f39b-300b-3f4d-0000-000000000000</id>
      <parentGroupId>02247fc8-6d6e-386b-0000-000000000000</parentGroupId>
      <backPressureDataSizeThreshold>1 GB</backPressureDataSizeThreshold>
      <backPressureObjectThreshold>10000</backPressureObjectThreshold>
      <destination>
        <groupId>02247fc8-6d6e-386b-0000-000000000000</groupId>
        <id>5ea6d01d-6557-3f54-0000-000000000000</id>
        <type>PROCESSOR</type>
      </destination>
      <flowFileExpiration>0 sec</flowFileExpiration>
      <labelIndex>1</labelIndex>
      <name></name>
      <selectedRelationships>failure</selectedRelationships>
      <source>
        <groupId>02247fc8-6d6e-386b-0000-000000000000</groupId>
        <id>f9d69938-e784-361c-0000-000000000000</id>
        <type>PROCESSOR</type>
      </source>
      <zIndex>0</zIndex>
    </connections>
    <connections>
      <id>4d7f9576-50c1-3dc2-0000-000000000000</id>
      <parentGroupId>02247fc8-6d6e-386b-0000-000000000000</parentGroupId>
      <backPressureDataSizeThreshold>1 GB</backPressureDataSizeThreshold>
      <backPressureObjectThreshold>10000</backPressureObjectThreshold>
      <destination>
        <groupId>02247fc8-6d6e-386b-0000-000000000000</groupId>
        <id>b0bfed8e-5442-3ee8-0000-000000000000</id>
        <type>PROCESSOR</type>
      </destination>
      <flowFileExpiration>0 sec</flowFileExpiration>
      <labelIndex>1</labelIndex>
      <name></name>
      <selectedRelationships>original</selectedRelationships>
      <source>
        <groupId>02247fc8-6d6e-386b-0000-000000000000</groupId>
        <id>6a12dc93-964a-3587-0000-000000000000</id>
        <type>PROCESSOR</type>
      </source>
      <zIndex>0</zIndex>
    </connections>
    <connections>
      <id>5ad8dfa4-6e4a-38fd-0000-000000000000</id>
      <parentGroupId>02247fc8-6d6e-386b-0000-000000000000</parentGroupId>
      <backPressureDataSizeThreshold>1 GB</backPressureDataSizeThreshold>
      <backPressureObjectThreshold>10000</backPressureObjectThreshold>
      <destination>
        <groupId>02247fc8-6d6e-386b-0000-000000000000</groupId>
        <id>b0bfed8e-5442-3ee8-0000-000000000000</id>
        <type>PROCESSOR</type>
      </destination>
      <flowFileExpiration>0 sec</flowFileExpiration>
      <labelIndex>1</labelIndex>
      <name></name>
      <selectedRelationships>unmatched</selectedRelationships>
      <source>
        <groupId>02247fc8-6d6e-386b-0000-000000000000</groupId>
        <id>d34db8ff-b684-387c-0000-000000000000</id>
        <type>PROCESSOR</type>
      </source>
      <zIndex>0</zIndex>
    </connections>
    <connections>
      <id>605ed967-cca0-3113-0000-000000000000</id>
      <parentGroupId>02247fc8-6d6e-386b-0000-000000000000</parentGroupId>
      <backPressureDataSizeThreshold>1 GB</backPressureDataSizeThreshold>
      <backPressureObjectThreshold>10000</backPressureObjectThreshold>
      <destination>
        <groupId>02247fc8-6d6e-386b-0000-000000000000</groupId>
        <id>d34db8ff-b684-387c-0000-000000000000</id>
        <type>PROCESSOR</type>
      </destination>
      <flowFileExpiration>0 sec</flowFileExpiration>
      <labelIndex>1</labelIndex>
      <name></name>
      <selectedRelationships>output stream</selectedRelationships>
      <source>
        <groupId>02247fc8-6d6e-386b-0000-000000000000</groupId>
        <id>6a12dc93-964a-3587-0000-000000000000</id>
        <type>PROCESSOR</type>
      </source>
      <zIndex>0</zIndex>
    </connections>
    <connections>
      <id>7af96ee9-0601-386a-0000-000000000000</id>
      <parentGroupId>02247fc8-6d6e-386b-0000-000000000000</parentGroupId>
      <backPressureDataSizeThreshold>1 GB</backPressureDataSizeThreshold>
      <backPressureObjectThreshold>10000</backPressureObjectThreshold>
      <destination>
        <groupId>02247fc8-6d6e-386b-0000-000000000000</groupId>
        <id>5b12ab24-fe05-3f7b-0000-000000000000</id>
        <type>PROCESSOR</type>
      </destination>
      <flowFileExpiration>0 sec</flowFileExpiration>
      <labelIndex>1</labelIndex>
      <name></name>
      <selectedRelationships>success</selectedRelationships>
      <source>
        <groupId>02247fc8-6d6e-386b-0000-000000000000</groupId>
        <id>f9d69938-e784-361c-0000-000000000000</id>
        <type>PROCESSOR</type>
      </source>
      <zIndex>0</zIndex>
    </connections>
    <processors>
      <id>80882335-0433-3769-0000-000000000000</id>
      <parentGroupId>02247fc8-6d6e-386b-0000-000000000000</parentGroupId>
      <position>
        <x>469.9501297171225</x>
        <y>7.4604847441459015</y>
      </position>
      <bundle>
        <artifact>nifi-standard-nar</artifact>
        <group>org.apache.nifi</group>
        <version>1.4.0</version>
      </bundle>
      <config>
        <bulletinLevel>WARN</bulletinLevel>
        <comments></comments>
        <concurrentlySchedulableTaskCount>0</concurrentlySchedulableTaskCount>
        <descriptors>
          <entry>
            <key>Destination</key>
            <value>
              <name>Destination</name>
            </value>
          </entry>
          <entry>
            <key>Return Type</key>
            <value>
              <name>Return Type</name>
            </value>
          </entry>
          <entry>
            <key>Path Not Found Behavior</key>
            <value>
              <name>Path Not Found Behavior</name>
            </value>
          </entry>
          <entry>
            <key>Null Value Representation</key>
            <value>
              <name>Null Value Representation</name>
            </value>
          </entry>
          <entry>
            <key>next</key>
            <value>
              <name>next</name>
            </value>
          </entry>
        </descriptors>
        <executionNode>ALL</executionNode>
        <lossTolerant>false</lossTolerant>
        <penaltyDuration>30 sec</penaltyDuration>
        <properties>
          <entry>
            <key>Destination</key>
            <value>flowfile-content</value>
          </entry>
          <entry>
            <key>Return Type</key>
            <value>auto-detect</value>
          </entry>
          <entry>
            <key>Path Not Found Behavior</key>
            <value>ignore</value>
          </entry>
          <entry>
            <key>Null Value Representation</key>
            <value>empty string</value>
          </entry>
          <entry>
            <key>next</key>
            <value>$.next</value>
          </entry>
        </properties>
        <runDurationMillis>0</runDurationMillis>
        <schedulingPeriod>0 sec</schedulingPeriod>
        <schedulingStrategy>EVENT_DRIVEN</schedulingStrategy>
        <yieldDuration>1 sec</yieldDuration>
      </config>
      <name>EvaluateJsonPath-NextRecord</name>
      <relationships>
        <autoTerminate>false</autoTerminate>
        <name>failure</name>
      </relationships>
      <relationships>
        <autoTerminate>false</autoTerminate>
        <name>matched</name>
      </relationships>
      <relationships>
        <autoTerminate>false</autoTerminate>
        <name>unmatched</name>
      </relationships>
      <state>RUNNING</state>
      <style></style>
      <type>org.apache.nifi.processors.standard.EvaluateJsonPath</type>
    </processors>
    <processors>
      <id>b0bfed8e-5442-3ee8-0000-000000000000</id>
      <parentGroupId>02247fc8-6d6e-386b-0000-000000000000</parentGroupId>
      <position>
        <x>628.9455441675225</x>
        <y>288.95444605990394</y>
      </position>
      <bundle>
        <artifact>nifi-standard-nar</artifact>
        <group>org.apache.nifi</group>
        <version>1.4.0</version>
      </bundle>
      <config>
        <bulletinLevel>WARN</bulletinLevel>
        <comments></comments>
        <concurrentlySchedulableTaskCount>0</concurrentlySchedulableTaskCount>
        <descriptors>
          <entry>
            <key>Log Level</key>
            <value>
              <name>Log Level</name>
            </value>
          </entry>
          <entry>
            <key>Log Payload</key>
            <value>
              <name>Log Payload</name>
            </value>
          </entry>
          <entry>
            <key>Attributes to Log</key>
            <value>
              <name>Attributes to Log</name>
            </value>
          </entry>
          <entry>
            <key>attributes-to-log-regex</key>
            <value>
              <name>attributes-to-log-regex</name>
            </value>
          </entry>
          <entry>
            <key>Attributes to Ignore</key>
            <value>
              <name>Attributes to Ignore</name>
            </value>
          </entry>
          <entry>
            <key>attributes-to-ignore-regex</key>
            <value>
              <name>attributes-to-ignore-regex</name>
            </value>
          </entry>
          <entry>
            <key>Log prefix</key>
            <value>
              <name>Log prefix</name>
            </value>
          </entry>
          <entry>
            <key>character-set</key>
            <value>
              <name>character-set</name>
            </value>
          </entry>
        </descriptors>
        <executionNode>ALL</executionNode>
        <lossTolerant>false</lossTolerant>
        <penaltyDuration>30 sec</penaltyDuration>
        <properties>
          <entry>
            <key>Log Level</key>
            <value>info</value>
          </entry>
          <entry>
            <key>Log Payload</key>
            <value>false</value>
          </entry>
          <entry>
            <key>Attributes to Log</key>
          </entry>
          <entry>
            <key>attributes-to-log-regex</key>
            <value>.*</value>
          </entry>
          <entry>
            <key>Attributes to Ignore</key>
          </entry>
          <entry>
            <key>attributes-to-ignore-regex</key>
          </entry>
          <entry>
            <key>Log prefix</key>
          </entry>
          <entry>
            <key>character-set</key>
            <value>US-ASCII</value>
          </entry>
        </properties>
        <runDurationMillis>0</runDurationMillis>
        <schedulingPeriod>0 sec</schedulingPeriod>
        <schedulingStrategy>EVENT_DRIVEN</schedulingStrategy>
        <yieldDuration>1 sec</yieldDuration>
      </config>
      <name>LogOriginalandUnmatched</name>
      <relationships>
        <autoTerminate>true</autoTerminate>
        <name>success</name>
      </relationships>
      <state>RUNNING</state>
      <style></style>
      <type>org.apache.nifi.processors.standard.LogAttribute</type>
    </processors>
    <processors>
      <id>c7e8f2c1-f381-3540-0000-000000000000</id>
      <parentGroupId>02247fc8-6d6e-386b-0000-000000000000</parentGroupId>
      <position>
        <x>5.567161755248094</x>
        <y>831.5668041282735</y>
      </position>
      <bundle>
        <artifact>nifi-aws-nar</artifact>
        <group>org.apache.nifi</group>
        <version>1.4.0</version>
      </bundle>
      <config>
        <bulletinLevel>WARN</bulletinLevel>
        <comments></comments>
        <concurrentlySchedulableTaskCount>1</concurrentlySchedulableTaskCount>
        <descriptors>
          <entry>
            <key>Queue URL</key>
            <value>
              <name>Queue URL</name>
            </value>
          </entry>
          <entry>
            <key>Access Key</key>
            <value>
              <name>Access Key</name>
            </value>
          </entry>
          <entry>
            <key>Secret Key</key>
            <value>
              <name>Secret Key</name>
            </value>
          </entry>
          <entry>
            <key>Credentials File</key>
            <value>
              <name>Credentials File</name>
            </value>
          </entry>
          <entry>
            <key>AWS Credentials Provider service</key>
            <value>
              <identifiesControllerService>org.apache.nifi.processors.aws.credentials.provider.service.AWSCredentialsProviderService</identifiesControllerService>
              <name>AWS Credentials Provider service</name>
            </value>
          </entry>
          <entry>
            <key>Region</key>
            <value>
              <name>Region</name>
            </value>
          </entry>
          <entry>
            <key>Delay</key>
            <value>
              <name>Delay</name>
            </value>
          </entry>
          <entry>
            <key>Communications Timeout</key>
            <value>
              <name>Communications Timeout</name>
            </value>
          </entry>
          <entry>
            <key>Proxy Host</key>
            <value>
              <name>Proxy Host</name>
            </value>
          </entry>
          <entry>
            <key>Proxy Host Port</key>
            <value>
              <name>Proxy Host Port</name>
            </value>
          </entry>
        </descriptors>
        <executionNode>ALL</executionNode>
        <lossTolerant>false</lossTolerant>
        <penaltyDuration>30 sec</penaltyDuration>
        <properties>
          <entry>
            <key>Queue URL</key>
            <value>https://sqs.us-east-1.amazonaws.com/038675855376/DPN-BagRecord-Sync</value>
          </entry>
          <entry>
            <key>Access Key</key>
          </entry>
          <entry>
            <key>Secret Key</key>
          </entry>
          <entry>
            <key>Credentials File</key>
          </entry>
          <entry>
            <key>AWS Credentials Provider service</key>
          </entry>
          <entry>
            <key>Region</key>
            <value>us-east-1</value>
          </entry>
          <entry>
            <key>Delay</key>
            <value>0 secs</value>
          </entry>
          <entry>
            <key>Communications Timeout</key>
            <value>30 secs</value>
          </entry>
          <entry>
            <key>Proxy Host</key>
          </entry>
          <entry>
            <key>Proxy Host Port</key>
          </entry>
        </properties>
        <runDurationMillis>0</runDurationMillis>
        <schedulingPeriod>0 sec</schedulingPeriod>
        <schedulingStrategy>TIMER_DRIVEN</schedulingStrategy>
        <yieldDuration>1 sec</yieldDuration>
      </config>
      <name>PutSQSRecordQueue</name>
      <relationships>
        <autoTerminate>false</autoTerminate>
        <name>failure</name>
      </relationships>
      <relationships>
        <autoTerminate>false</autoTerminate>
        <name>success</name>
      </relationships>
      <state>RUNNING</state>
      <style></style>
      <type>org.apache.nifi.processors.aws.sqs.PutSQS</type>
    </processors>
    <processors>
      <id>d34db8ff-b684-387c-0000-000000000000</id>
      <parentGroupId>02247fc8-6d6e-386b-0000-000000000000</parentGroupId>
      <position>
        <x>0.0</x>
        <y>398.211944444644</y>
      </position>
      <bundle>
        <artifact>nifi-standard-nar</artifact>
        <group>org.apache.nifi</group>
        <version>1.4.0</version>
      </bundle>
      <config>
        <bulletinLevel>WARN</bulletinLevel>
        <comments></comments>
        <concurrentlySchedulableTaskCount>0</concurrentlySchedulableTaskCount>
        <descriptors>
          <entry>
            <key>Destination</key>
            <value>
              <name>Destination</name>
            </value>
          </entry>
          <entry>
            <key>Return Type</key>
            <value>
              <name>Return Type</name>
            </value>
          </entry>
          <entry>
            <key>Path Not Found Behavior</key>
            <value>
              <name>Path Not Found Behavior</name>
            </value>
          </entry>
          <entry>
            <key>Null Value Representation</key>
            <value>
              <name>Null Value Representation</name>
            </value>
          </entry>
          <entry>
            <key>results</key>
            <value>
              <name>results</name>
            </value>
          </entry>
        </descriptors>
        <executionNode>ALL</executionNode>
        <lossTolerant>false</lossTolerant>
        <penaltyDuration>30 sec</penaltyDuration>
        <properties>
          <entry>
            <key>Destination</key>
            <value>flowfile-content</value>
          </entry>
          <entry>
            <key>Return Type</key>
            <value>auto-detect</value>
          </entry>
          <entry>
            <key>Path Not Found Behavior</key>
            <value>ignore</value>
          </entry>
          <entry>
            <key>Null Value Representation</key>
            <value>empty string</value>
          </entry>
          <entry>
            <key>results</key>
            <value>$.results[0]</value>
          </entry>
        </properties>
        <runDurationMillis>0</runDurationMillis>
        <schedulingPeriod>0 sec</schedulingPeriod>
        <schedulingStrategy>EVENT_DRIVEN</schedulingStrategy>
        <yieldDuration>1 sec</yieldDuration>
      </config>
      <name>ReturnBagMetadata</name>
      <relationships>
        <autoTerminate>false</autoTerminate>
        <name>failure</name>
      </relationships>
      <relationships>
        <autoTerminate>false</autoTerminate>
        <name>matched</name>
      </relationships>
      <relationships>
        <autoTerminate>false</autoTerminate>
        <name>unmatched</name>
      </relationships>
      <state>RUNNING</state>
      <style></style>
      <type>org.apache.nifi.processors.standard.EvaluateJsonPath</type>
    </processors>
    <processors>
      <id>f9d69938-e784-361c-0000-000000000000</id>
      <parentGroupId>02247fc8-6d6e-386b-0000-000000000000</parentGroupId>
      <position>
        <x>1028.8612600949978</x>
        <y>8.559648166549891</y>
      </position>
      <bundle>
        <artifact>nifi-standard-nar</artifact>
        <group>org.apache.nifi</group>
        <version>1.4.0</version>
      </bundle>
      <config>
        <bulletinLevel>WARN</bulletinLevel>
        <comments></comments>
        <concurrentlySchedulableTaskCount>0</concurrentlySchedulableTaskCount>
        <descriptors>
          <entry>
            <key>Regular Expression</key>
            <value>
              <name>Regular Expression</name>
            </value>
          </entry>
          <entry>
            <key>Replacement Value</key>
            <value>
              <name>Replacement Value</name>
            </value>
          </entry>
          <entry>
            <key>Character Set</key>
            <value>
              <name>Character Set</name>
            </value>
          </entry>
          <entry>
            <key>Maximum Buffer Size</key>
            <value>
              <name>Maximum Buffer Size</name>
            </value>
          </entry>
          <entry>
            <key>Replacement Strategy</key>
            <value>
              <name>Replacement Strategy</name>
            </value>
          </entry>
          <entry>
            <key>Evaluation Mode</key>
            <value>
              <name>Evaluation Mode</name>
            </value>
          </entry>
        </descriptors>
        <executionNode>ALL</executionNode>
        <lossTolerant>false</lossTolerant>
        <penaltyDuration>30 sec</penaltyDuration>
        <properties>
          <entry>
            <key>Regular Expression</key>
            <value>(.*page_size=1)(.*)</value>
          </entry>
          <entry>
            <key>Replacement Value</key>
            <value>$1</value>
          </entry>
          <entry>
            <key>Character Set</key>
            <value>UTF-8</value>
          </entry>
          <entry>
            <key>Maximum Buffer Size</key>
            <value>1 MB</value>
          </entry>
          <entry>
            <key>Replacement Strategy</key>
            <value>Regex Replace</value>
          </entry>
          <entry>
            <key>Evaluation Mode</key>
            <value>Line-by-Line</value>
          </entry>
        </properties>
        <runDurationMillis>0</runDurationMillis>
        <schedulingPeriod>0 sec</schedulingPeriod>
        <schedulingStrategy>EVENT_DRIVEN</schedulingStrategy>
        <yieldDuration>1 sec</yieldDuration>
      </config>
      <name>ReplaceText</name>
      <relationships>
        <autoTerminate>false</autoTerminate>
        <name>failure</name>
      </relationships>
      <relationships>
        <autoTerminate>false</autoTerminate>
        <name>success</name>
      </relationships>
      <state>RUNNING</state>
      <style></style>
      <type>org.apache.nifi.processors.standard.ReplaceText</type>
    </processors>
    <processors>
      <id>02cb0aec-fd02-3a41-0000-000000000000</id>
      <parentGroupId>02247fc8-6d6e-386b-0000-000000000000</parentGroupId>
      <position>
        <x>1.6920466002831631</x>
        <y>0.0</y>
      </position>
      <bundle>
        <artifact>nifi-aws-nar</artifact>
        <group>org.apache.nifi</group>
        <version>1.4.0</version>
      </bundle>
      <config>
        <bulletinLevel>WARN</bulletinLevel>
        <comments></comments>
        <concurrentlySchedulableTaskCount>1</concurrentlySchedulableTaskCount>
        <descriptors>
          <entry>
            <key>Queue URL</key>
            <value>
              <name>Queue URL</name>
            </value>
          </entry>
          <entry>
            <key>Auto Delete Messages</key>
            <value>
              <name>Auto Delete Messages</name>
            </value>
          </entry>
          <entry>
            <key>Access Key</key>
            <value>
              <name>Access Key</name>
            </value>
          </entry>
          <entry>
            <key>Secret Key</key>
            <value>
              <name>Secret Key</name>
            </value>
          </entry>
          <entry>
            <key>Credentials File</key>
            <value>
              <name>Credentials File</name>
            </value>
          </entry>
          <entry>
            <key>AWS Credentials Provider service</key>
            <value>
              <identifiesControllerService>org.apache.nifi.processors.aws.credentials.provider.service.AWSCredentialsProviderService</identifiesControllerService>
              <name>AWS Credentials Provider service</name>
            </value>
          </entry>
          <entry>
            <key>Region</key>
            <value>
              <name>Region</name>
            </value>
          </entry>
          <entry>
            <key>Batch Size</key>
            <value>
              <name>Batch Size</name>
            </value>
          </entry>
          <entry>
            <key>Communications Timeout</key>
            <value>
              <name>Communications Timeout</name>
            </value>
          </entry>
          <entry>
            <key>Character Set</key>
            <value>
              <name>Character Set</name>
            </value>
          </entry>
          <entry>
            <key>Visibility Timeout</key>
            <value>
              <name>Visibility Timeout</name>
            </value>
          </entry>
          <entry>
            <key>Receive Message Wait Time</key>
            <value>
              <name>Receive Message Wait Time</name>
            </value>
          </entry>
          <entry>
            <key>Proxy Host</key>
            <value>
              <name>Proxy Host</name>
            </value>
          </entry>
          <entry>
            <key>Proxy Host Port</key>
            <value>
              <name>Proxy Host Port</name>
            </value>
          </entry>
        </descriptors>
        <executionNode>ALL</executionNode>
        <lossTolerant>false</lossTolerant>
        <penaltyDuration>30 sec</penaltyDuration>
        <properties>
          <entry>
            <key>Queue URL</key>
            <value>https://sqs.us-east-1.amazonaws.com/038675855376/DPN-NiFi-Flow</value>
          </entry>
          <entry>
            <key>Auto Delete Messages</key>
            <value>true</value>
          </entry>
          <entry>
            <key>Access Key</key>
          </entry>
          <entry>
            <key>Secret Key</key>
          </entry>
          <entry>
            <key>Credentials File</key>
          </entry>
          <entry>
            <key>AWS Credentials Provider service</key>
          </entry>
          <entry>
            <key>Region</key>
            <value>us-east-1</value>
          </entry>
          <entry>
            <key>Batch Size</key>
            <value>1</value>
          </entry>
          <entry>
            <key>Communications Timeout</key>
            <value>90 secs</value>
          </entry>
          <entry>
            <key>Character Set</key>
            <value>UTF-8</value>
          </entry>
          <entry>
            <key>Visibility Timeout</key>
            <value>5 mins</value>
          </entry>
          <entry>
            <key>Receive Message Wait Time</key>
            <value>0 sec</value>
          </entry>
          <entry>
            <key>Proxy Host</key>
          </entry>
          <entry>
            <key>Proxy Host Port</key>
          </entry>
        </properties>
        <runDurationMillis>0</runDurationMillis>
        <schedulingPeriod>5 sec</schedulingPeriod>
        <schedulingStrategy>TIMER_DRIVEN</schedulingStrategy>
        <yieldDuration>1 sec</yieldDuration>
      </config>
      <name>GetSQS</name>
      <relationships>
        <autoTerminate>false</autoTerminate>
        <name>success</name>
      </relationships>
      <state>RUNNING</state>
      <style></style>
      <type>org.apache.nifi.processors.aws.sqs.GetSQS</type>
    </processors>
    <processors>
      <id>0d0ce7fd-4ad9-3a20-0000-000000000000</id>
      <parentGroupId>02247fc8-6d6e-386b-0000-000000000000</parentGroupId>
      <position>
        <x>1481.5505849546203</x>
        <y>741.278232274204</y>
      </position>
      <bundle>
        <artifact>nifi-standard-nar</artifact>
        <group>org.apache.nifi</group>
        <version>1.4.0</version>
      </bundle>
      <config>
        <bulletinLevel>WARN</bulletinLevel>
        <comments></comments>
        <concurrentlySchedulableTaskCount>0</concurrentlySchedulableTaskCount>
        <descriptors>
          <entry>
            <key>Log Level</key>
            <value>
              <name>Log Level</name>
            </value>
          </entry>
          <entry>
            <key>Log Payload</key>
            <value>
              <name>Log Payload</name>
            </value>
          </entry>
          <entry>
            <key>Attributes to Log</key>
            <value>
              <name>Attributes to Log</name>
            </value>
          </entry>
          <entry>
            <key>attributes-to-log-regex</key>
            <value>
              <name>attributes-to-log-regex</name>
            </value>
          </entry>
          <entry>
            <key>Attributes to Ignore</key>
            <value>
              <name>Attributes to Ignore</name>
            </value>
          </entry>
          <entry>
            <key>attributes-to-ignore-regex</key>
            <value>
              <name>attributes-to-ignore-regex</name>
            </value>
          </entry>
          <entry>
            <key>Log prefix</key>
            <value>
              <name>Log prefix</name>
            </value>
          </entry>
          <entry>
            <key>character-set</key>
            <value>
              <name>character-set</name>
            </value>
          </entry>
        </descriptors>
        <executionNode>ALL</executionNode>
        <lossTolerant>false</lossTolerant>
        <penaltyDuration>30 sec</penaltyDuration>
        <properties>
          <entry>
            <key>Log Level</key>
            <value>info</value>
          </entry>
          <entry>
            <key>Log Payload</key>
            <value>true</value>
          </entry>
          <entry>
            <key>Attributes to Log</key>
          </entry>
          <entry>
            <key>attributes-to-log-regex</key>
            <value>.*</value>
          </entry>
          <entry>
            <key>Attributes to Ignore</key>
          </entry>
          <entry>
            <key>attributes-to-ignore-regex</key>
          </entry>
          <entry>
            <key>Log prefix</key>
          </entry>
          <entry>
            <key>character-set</key>
            <value>US-ASCII</value>
          </entry>
        </properties>
        <runDurationMillis>0</runDurationMillis>
        <schedulingPeriod>0 sec</schedulingPeriod>
        <schedulingStrategy>EVENT_DRIVEN</schedulingStrategy>
        <yieldDuration>1 sec</yieldDuration>
      </config>
      <name>LogSuccess</name>
      <relationships>
        <autoTerminate>true</autoTerminate>
        <name>success</name>
      </relationships>
      <state>STOPPED</state>
      <style></style>
      <type>org.apache.nifi.processors.standard.LogAttribute</type>
    </processors>
    <processors>
      <id>5b12ab24-fe05-3f7b-0000-000000000000</id>
      <parentGroupId>02247fc8-6d6e-386b-0000-000000000000</parentGroupId>
      <position>
        <x>1478.0903768586404</x>
        <y>8.689263092998203</y>
      </position>
      <bundle>
        <artifact>nifi-aws-nar</artifact>
        <group>org.apache.nifi</group>
        <version>1.4.0</version>
      </bundle>
      <config>
        <bulletinLevel>WARN</bulletinLevel>
        <comments></comments>
        <concurrentlySchedulableTaskCount>1</concurrentlySchedulableTaskCount>
        <descriptors>
          <entry>
            <key>Queue URL</key>
            <value>
              <name>Queue URL</name>
            </value>
          </entry>
          <entry>
            <key>Access Key</key>
            <value>
              <name>Access Key</name>
            </value>
          </entry>
          <entry>
            <key>Secret Key</key>
            <value>
              <name>Secret Key</name>
            </value>
          </entry>
          <entry>
            <key>Credentials File</key>
            <value>
              <name>Credentials File</name>
            </value>
          </entry>
          <entry>
            <key>AWS Credentials Provider service</key>
            <value>
              <identifiesControllerService>org.apache.nifi.processors.aws.credentials.provider.service.AWSCredentialsProviderService</identifiesControllerService>
              <name>AWS Credentials Provider service</name>
            </value>
          </entry>
          <entry>
            <key>Region</key>
            <value>
              <name>Region</name>
            </value>
          </entry>
          <entry>
            <key>Delay</key>
            <value>
              <name>Delay</name>
            </value>
          </entry>
          <entry>
            <key>Communications Timeout</key>
            <value>
              <name>Communications Timeout</name>
            </value>
          </entry>
          <entry>
            <key>Proxy Host</key>
            <value>
              <name>Proxy Host</name>
            </value>
          </entry>
          <entry>
            <key>Proxy Host Port</key>
            <value>
              <name>Proxy Host Port</name>
            </value>
          </entry>
        </descriptors>
        <executionNode>ALL</executionNode>
        <lossTolerant>false</lossTolerant>
        <penaltyDuration>30 sec</penaltyDuration>
        <properties>
          <entry>
            <key>Queue URL</key>
            <value>https://sqs.us-east-1.amazonaws.com/038675855376/DPN-NiFi-Flow</value>
          </entry>
          <entry>
            <key>Access Key</key>
          </entry>
          <entry>
            <key>Secret Key</key>
          </entry>
          <entry>
            <key>Credentials File</key>
          </entry>
          <entry>
            <key>AWS Credentials Provider service</key>
          </entry>
          <entry>
            <key>Region</key>
            <value>us-east-1</value>
          </entry>
          <entry>
            <key>Delay</key>
            <value>0 secs</value>
          </entry>
          <entry>
            <key>Communications Timeout</key>
            <value>30 secs</value>
          </entry>
          <entry>
            <key>Proxy Host</key>
          </entry>
          <entry>
            <key>Proxy Host Port</key>
          </entry>
        </properties>
        <runDurationMillis>0</runDurationMillis>
        <schedulingPeriod>0 sec</schedulingPeriod>
        <schedulingStrategy>TIMER_DRIVEN</schedulingStrategy>
        <yieldDuration>1 sec</yieldDuration>
      </config>
      <name>PutSQSnextRecord</name>
      <relationships>
        <autoTerminate>false</autoTerminate>
        <name>failure</name>
      </relationships>
      <relationships>
        <autoTerminate>false</autoTerminate>
        <name>success</name>
      </relationships>
      <state>RUNNING</state>
      <style></style>
      <type>org.apache.nifi.processors.aws.sqs.PutSQS</type>
    </processors>
    <processors>
      <id>5ea6d01d-6557-3f54-0000-000000000000</id>
      <parentGroupId>02247fc8-6d6e-386b-0000-000000000000</parentGroupId>
      <position>
        <x>1068.99725764592</x>
        <y>377.6033791461906</y>
      </position>
      <bundle>
        <artifact>nifi-standard-nar</artifact>
        <group>org.apache.nifi</group>
        <version>1.4.0</version>
      </bundle>
      <config>
        <bulletinLevel>WARN</bulletinLevel>
        <comments></comments>
        <concurrentlySchedulableTaskCount>0</concurrentlySchedulableTaskCount>
        <descriptors>
          <entry>
            <key>Log Level</key>
            <value>
              <name>Log Level</name>
            </value>
          </entry>
          <entry>
            <key>Log Payload</key>
            <value>
              <name>Log Payload</name>
            </value>
          </entry>
          <entry>
            <key>Attributes to Log</key>
            <value>
              <name>Attributes to Log</name>
            </value>
          </entry>
          <entry>
            <key>attributes-to-log-regex</key>
            <value>
              <name>attributes-to-log-regex</name>
            </value>
          </entry>
          <entry>
            <key>Attributes to Ignore</key>
            <value>
              <name>Attributes to Ignore</name>
            </value>
          </entry>
          <entry>
            <key>attributes-to-ignore-regex</key>
            <value>
              <name>attributes-to-ignore-regex</name>
            </value>
          </entry>
          <entry>
            <key>Log prefix</key>
            <value>
              <name>Log prefix</name>
            </value>
          </entry>
          <entry>
            <key>character-set</key>
            <value>
              <name>character-set</name>
            </value>
          </entry>
        </descriptors>
        <executionNode>ALL</executionNode>
        <lossTolerant>false</lossTolerant>
        <penaltyDuration>30 sec</penaltyDuration>
        <properties>
          <entry>
            <key>Log Level</key>
            <value>info</value>
          </entry>
          <entry>
            <key>Log Payload</key>
            <value>false</value>
          </entry>
          <entry>
            <key>Attributes to Log</key>
          </entry>
          <entry>
            <key>attributes-to-log-regex</key>
            <value>.*</value>
          </entry>
          <entry>
            <key>Attributes to Ignore</key>
          </entry>
          <entry>
            <key>attributes-to-ignore-regex</key>
          </entry>
          <entry>
            <key>Log prefix</key>
          </entry>
          <entry>
            <key>character-set</key>
            <value>US-ASCII</value>
          </entry>
        </properties>
        <runDurationMillis>0</runDurationMillis>
        <schedulingPeriod>0 sec</schedulingPeriod>
        <schedulingStrategy>EVENT_DRIVEN</schedulingStrategy>
        <yieldDuration>1 sec</yieldDuration>
      </config>
      <name>LogFailure</name>
      <relationships>
        <autoTerminate>true</autoTerminate>
        <name>success</name>
      </relationships>
      <state>RUNNING</state>
      <style></style>
      <type>org.apache.nifi.processors.standard.LogAttribute</type>
    </processors>
    <processors>
      <id>6a12dc93-964a-3587-0000-000000000000</id>
      <parentGroupId>02247fc8-6d6e-386b-0000-000000000000</parentGroupId>
      <position>
        <x>2.2314115283758724</x>
        <y>203.6704114807875</y>
      </position>
      <bundle>
        <artifact>nifi-standard-nar</artifact>
        <group>org.apache.nifi</group>
        <version>1.4.0</version>
      </bundle>
      <config>
        <bulletinLevel>WARN</bulletinLevel>
        <comments></comments>
        <concurrentlySchedulableTaskCount>0</concurrentlySchedulableTaskCount>
        <descriptors>
          <entry>
            <key>Command Arguments</key>
            <value>
              <name>Command Arguments</name>
            </value>
          </entry>
          <entry>
            <key>Command Path</key>
            <value>
              <name>Command Path</name>
            </value>
          </entry>
          <entry>
            <key>Ignore STDIN</key>
            <value>
              <name>Ignore STDIN</name>
            </value>
          </entry>
          <entry>
            <key>Working Directory</key>
            <value>
              <name>Working Directory</name>
            </value>
          </entry>
          <entry>
            <key>Argument Delimiter</key>
            <value>
              <name>Argument Delimiter</name>
            </value>
          </entry>
          <entry>
            <key>Output Destination Attribute</key>
            <value>
              <name>Output Destination Attribute</name>
            </value>
          </entry>
          <entry>
            <key>Max Attribute Length</key>
            <value>
              <name>Max Attribute Length</name>
            </value>
          </entry>
        </descriptors>
        <executionNode>ALL</executionNode>
        <lossTolerant>false</lossTolerant>
        <penaltyDuration>30 sec</penaltyDuration>
        <properties>
          <entry>
            <key>Command Arguments</key>
          </entry>
          <entry>
            <key>Command Path</key>
            <value>/opt/dpn/get_api_endpoint.py</value>
          </entry>
          <entry>
            <key>Ignore STDIN</key>
            <value>false</value>
          </entry>
          <entry>
            <key>Working Directory</key>
            <value>/tmp/dpn</value>
          </entry>
          <entry>
            <key>Argument Delimiter</key>
            <value>;</value>
          </entry>
          <entry>
            <key>Output Destination Attribute</key>
          </entry>
          <entry>
            <key>Max Attribute Length</key>
            <value>512</value>
          </entry>
        </properties>
        <runDurationMillis>0</runDurationMillis>
        <schedulingPeriod>0 sec</schedulingPeriod>
        <schedulingStrategy>EVENT_DRIVEN</schedulingStrategy>
        <yieldDuration>1 sec</yieldDuration>
      </config>
      <name>RetrieveviaAPI</name>
      <relationships>
        <autoTerminate>false</autoTerminate>
        <name>original</name>
      </relationships>
      <relationships>
        <autoTerminate>false</autoTerminate>
        <name>output stream</name>
      </relationships>
      <state>RUNNING</state>
      <style></style>
      <type>org.apache.nifi.processors.standard.ExecuteStreamCommand</type>
    </processors>
    <processors>
      <id>7ce9fc67-bfde-3483-0000-000000000000</id>
      <parentGroupId>02247fc8-6d6e-386b-0000-000000000000</parentGroupId>
      <position>
        <x>5.9672814845550874</x>
        <y>603.3091130824386</y>
      </position>
      <bundle>
        <artifact>nifi-standard-nar</artifact>
        <group>org.apache.nifi</group>
        <version>1.4.0</version>
      </bundle>
      <config>
        <bulletinLevel>WARN</bulletinLevel>
        <comments></comments>
        <concurrentlySchedulableTaskCount>0</concurrentlySchedulableTaskCount>
        <descriptors>
          <entry>
            <key>Regular Expression</key>
            <value>
              <name>Regular Expression</name>
            </value>
          </entry>
          <entry>
            <key>Replacement Value</key>
            <value>
              <name>Replacement Value</name>
            </value>
          </entry>
          <entry>
            <key>Character Set</key>
            <value>
              <name>Character Set</name>
            </value>
          </entry>
          <entry>
            <key>Maximum Buffer Size</key>
            <value>
              <name>Maximum Buffer Size</name>
            </value>
          </entry>
          <entry>
            <key>Replacement Strategy</key>
            <value>
              <name>Replacement Strategy</name>
            </value>
          </entry>
          <entry>
            <key>Evaluation Mode</key>
            <value>
              <name>Evaluation Mode</name>
            </value>
          </entry>
        </descriptors>
        <executionNode>ALL</executionNode>
        <lossTolerant>false</lossTolerant>
        <penaltyDuration>30 sec</penaltyDuration>
        <properties>
          <entry>
            <key>Regular Expression</key>
            <value>(^.)(.$)</value>
          </entry>
          <entry>
            <key>Replacement Value</key>
            <value></value>
          </entry>
          <entry>
            <key>Character Set</key>
            <value>UTF-8</value>
          </entry>
          <entry>
            <key>Maximum Buffer Size</key>
            <value>1 MB</value>
          </entry>
          <entry>
            <key>Replacement Strategy</key>
            <value>Regex Replace</value>
          </entry>
          <entry>
            <key>Evaluation Mode</key>
            <value>Entire text</value>
          </entry>
        </properties>
        <runDurationMillis>0</runDurationMillis>
        <schedulingPeriod>0 sec</schedulingPeriod>
        <schedulingStrategy>EVENT_DRIVEN</schedulingStrategy>
        <yieldDuration>1 sec</yieldDuration>
      </config>
      <name>extractsinglerecord</name>
      <relationships>
        <autoTerminate>false</autoTerminate>
        <name>failure</name>
      </relationships>
      <relationships>
        <autoTerminate>false</autoTerminate>
        <name>success</name>
      </relationships>
      <state>RUNNING</state>
      <style></style>
      <type>org.apache.nifi.processors.standard.ReplaceText</type>
    </processors>
  </snippet>
  <timestamp>11/08/2017 18:40:18 UTC</timestamp>
</template>